api/__init__.py
api/account.py
api/providers.py
api/serializer.py
api/signer.py
api/transactions.py
near_api/__init__.py
near_api/account.py
near_api/providers.py
near_api/serializer.py
near_api/signer.py
near_api/transactions.py
test/__init__.py
test/config.py
test/test_account.py
test/test_provider.py
test/utils.py
near_client-0.2.0.dist-info/LICENSE
near_client-0.2.0.dist-info/LICENSE-APACHE
near_client-0.2.0.dist-info/METADATA
near_client-0.2.0.dist-info/WHEEL
near_client-0.2.0.dist-info/top_level.txt
near_client-0.2.0.dist-info/RECORD
