Metadata-Version: 2.1
Name: near-client
Version: 0.2.0
Summary: UNKNOWN
Home-page: https://github.com/calimero-is-near/near-py-client
Author: NEAR Inc
License: MIT
Platform: UNKNOWN
License-File: LICENSE
License-File: LICENSE-APACHE
Requires-Dist: requests
Requires-Dist: base58
Requires-Dist: ed25519
